photo_to_excel/__init__.py
photo_to_excel/helpers.py
photo_to_excel/photo_to_excel.py
photo_to_excel-1.0.0.dist-info/LICENSE
photo_to_excel-1.0.0.dist-info/METADATA
photo_to_excel-1.0.0.dist-info/WHEEL
photo_to_excel-1.0.0.dist-info/RECORD
