Metadata-Version: 2.3
Name: photo_to_excel
Version: 1.0.0
Summary: Covert your photos to Excel file
Author: Julia Marcinkowska
Author-email: juliamarcinkowska98@gmail.com
Maintainer: Julia Marcinkowska
Maintainer-email: juliamarcinkowska98@gmail.com
Requires-Python: >=3.9.6, <3.12
Classifier: Programming Language :: Python :: 3
Classifier: Operating System :: MacOS
Requires-Dist: openpyxl (>=3.1.5)
Requires-Dist: pillow (>=11.1.0)
Project-URL: Homepage, https://github.com/juliam98/photo_to_excel
Project-URL: Issues, https://github.com/juliam98/photo_to_excel/issues
